DSreader/__init__.py
DSreader/mapdata.py
DSreader/mapelements.py
DSreader/maptables.py
DSreader/data/beheertypen_kenmerkendheid.csv
DSreader-0.0.1.dist-info/LICENSE
DSreader-0.0.1.dist-info/METADATA
DSreader-0.0.1.dist-info/WHEEL
DSreader-0.0.1.dist-info/top_level.txt
DSreader-0.0.1.dist-info/RECORD
