Metadata-Version: 2.1
Name: DSreader
Version: 0.0.1
Summary: Read data from Digital Standard vegetation mapping projects
Home-page: https://github.com/tdmeij/DSreader
Author: Thomas de Meij
Author-email: thomasdemeij@gmail.com
License: MIT
Platform: UNKNOWN
License-File: LICENSE
Requires-Dist: pandas
Requires-Dist: numpy
Requires-Dist: geopandas
Requires-Dist: fiona
Requires-Dist: json
Requires-Dist: pyodbc
Requires-Dist: plotly
